pyXhCustApp.py
pyXhCustApp-0.0.4.dist-info/LICENSE.txt
pyXhCustApp-0.0.4.dist-info/METADATA
pyXhCustApp-0.0.4.dist-info/WHEEL
pyXhCustApp-0.0.4.dist-info/top_level.txt
pyXhCustApp-0.0.4.dist-info/RECORD
