Metadata-Version: 2.1
Name: pyXhCustApp
Version: 0.0.4
Summary: Custom App Environment
Home-page: https://github.com/xh-dev-py/pyXhCustApp
Author: xethhung
Author-email: pypi@xethh.dev
License: UNKNOWN
Platform: UNKNOWN
Provides-Extra: dev
Requires-Dist: pytest (>=3.7) ; extra == 'dev'
